{
	"rules": {
		/**
		 * Must not duplicate **ID**
		 *
		 * Be able to avoid problems in assistive technologies from the viewpoint of machine readability.
		 *
		 * @see https://www.w3.org/WAI/WCAG21/Techniques/html/H93.html
		 */
		"id-duplication": true,

		"invalid-attr": {
			"options": {
				"disallowAttrs": [
					/**
					 * Disallow `accesskey` attr
					 *
					 * @see https://developer.mozilla.org/en-US/docs/Web/HTML/Global_attributes/accesskey#accessibility_concerns
					 */
					"accesskey"
				],
				"allowAttrs": [
					{
						/**
						 * `tabindex` attr only `-1` or `0`
						 *
						 * @see https://developer.mozilla.org/en-US/docs/Web/HTML/Global_attributes/tabindex#accessibility_concerns
						 */
						"name": "tabindex",
						"value": {
							"enum": ["-1", "0"]
						}
					}
				]
			}
		},

		/**
		 * `<label>` should have control
		 *
		 */
		"label-has-control": true,

		/**
		 * Use **landmark**
		 *
		 * @see https://www.w3.org/TR/wai-aria-practices/examples/landmarks/
		 */
		"landmark-roles": true,

		/**
		 * **Popover** trigger and target must be adjacent
		 *
		 */
		"neighbor-popovers": true,

		/**
		 * No consecutive `<br>`
		 */
		"no-consecutive-br": true,

		/**
		 * No refer to no existent **ID**
		 */
		"no-refer-to-non-existent-id": true,

		/**
		 * Require **accessible name**
		 */
		"require-accessible-name": true,

		/**
		 * Require `<h1>`
		 *
		 */
		"required-h1": true,

		/**
		 * Align row and column
		 *
		 */
		"table-row-column-alignment": true,

		/**
		 * Use `<ul>`
		 *
		 */
		"use-list": true,

		/**
		 * Conform to **WAI-ARIA**
		 *
		 */
		"wai-aria": true
	},
	"nodeRules": [
		{
			"selector": ":where(html)",
			"rules": {
				/**
				 * Require `<html lang>`
				 *
				 */
				"required-attr": ["lang"]
			}
		},
		{
			"selector": ":where(abbr)",
			"rules": {
				/**
				 * Require `<abbr title>`
				 */
				"required-attr": ["title"]
			}
		},
		{
			"selector": ":where(video, audio)",
			"rules": {
				/**
				 * Require `<track>`
				 *
				 */
				"required-element": ["track"]
			}
		},
		{
			"selector": ":where(video[autoplay])",
			"rules": {
				/**
				 * Require `<video muted>`
				 *
				 */
				"required-attr": ["muted"]
			}
		},
		{
			/**
			 * No merge cells
			 *
			 */
			"selector": ":where(th, td)",
			"rules": {
				"invalid-attr": {
					"options": {
						"disallowAttrs": ["colspan", "rowspan"]
					}
				}
			}
		},
		{
			"selector": ":where(summary)",
			"rules": {
				/**
				 * `<summary>` no contains interactive contents
				 *
				 * There is a case where an assistive technology can't access contents, or contents don't propagate a mouse event to `<summary>`.
				 *
				 * > The link is not discoverable at all to JAWS when navigating with its virtual cursor.
				 * > If navigating to the summary element via the Tab key,
				 * > JAWS announces "example text, button" as the name and role of the element.
				 * > If hitting Tab key again, JAWS again announces "example text,
				 * > button" even though keyboard focus is on the link.
				 *
				 * @see https://github.com/whatwg/html/issues/2272#issuecomment-1242415594
				 */
				"disallowed-element": [":model(interactive)"]
			}
		},
		{
			"selector": ":where(:not(dialog, dialog *))",
			"rules": {
				"invalid-attr": {
					"options": {
						"disallowAttrs": [
							/**
							 * Disallow `autofocus` attr to except in the dialog scope
							 *
							 * Don't take away a focus to forced. However,  the `dialog` element and its descendants allow it.
							 *
							 * @see https://developer.mozilla.org/en-US/docs/Web/HTML/Global_attributes/autofocus#accessibility_considerations
							 */
							"autofocus"
						]
					}
				}
			}
		}
	]
}
