{
	"tagName": "script",
	"citeFrom": "https://developer.mozilla.org/en-US/docs/Web/HTML/Element/script",
	"attr": [
		"#global",
		{
			"name": "async",
			"description": "This is a Boolean attribute indicating that the browser should, if possible, execute the script asynchronously."
		}
	],
	"categories": [
		"Metadata",
		"Flow",
		"Phrasing"
	],
	"content": "Dynamic script such as text/javascript.",
	"omission": "None, both the starting and ending tag are mandatory.",
	"parents": "Any element that accepts metadata content, or any element that accepts phrasing content.",
	"roles": [
		"None"
	]
}