{
	"tag": "body",
	"ref": "https://html.spec.whatwg.org/multipage/sections.html#the-body-element",
	"global": {
		"#HTMLGlobalAttrs": true,
		"#GlobalEventAttrs": true,
		"#DocumentElementEventAttrs": true,
		"#ARIAAttrs": true
	},
	"attributes": {
		"onafterprint": {
			"ref": "https://html.spec.whatwg.org/multipage/webappapis.html#handler-window-onafterprint",
			"type": "FunctionBody"
		},
		"onbeforeprint": {
			"ref": "https://html.spec.whatwg.org/multipage/webappapis.html#handler-window-onbeforeprint",
			"type": "FunctionBody"
		},
		"onbeforeunload": {
			"ref": "https://html.spec.whatwg.org/multipage/webappapis.html#handler-window-onbeforeunload",
			"type": "FunctionBody"
		},
		"onhashchange": {
			"ref": "https://html.spec.whatwg.org/multipage/webappapis.html#handler-window-onhashchange",
			"type": "FunctionBody"
		},
		"onlanguagechange": {
			"ref": "https://html.spec.whatwg.org/multipage/webappapis.html#handler-window-onlanguagechange",
			"type": "FunctionBody"
		},
		"onmessage": {
			"ref": "https://html.spec.whatwg.org/multipage/webappapis.html#handler-window-onmessage",
			"type": "FunctionBody"
		},
		"onmessageerror": {
			"ref": "https://html.spec.whatwg.org/multipage/webappapis.html#handler-window-onmessageerror",
			"type": "FunctionBody"
		},
		"onoffline": {
			"ref": "https://html.spec.whatwg.org/multipage/webappapis.html#handler-window-onoffline",
			"type": "FunctionBody"
		},
		"ononline": {
			"ref": "https://html.spec.whatwg.org/multipage/webappapis.html#handler-window-ononline",
			"type": "FunctionBody"
		},
		"onpagehide": {
			"ref": "https://html.spec.whatwg.org/multipage/webappapis.html#handler-window-onpagehide",
			"type": "FunctionBody"
		},
		"onpageshow": {
			"ref": "https://html.spec.whatwg.org/multipage/webappapis.html#handler-window-onpageshow",
			"type": "FunctionBody"
		},
		"onpopstate": {
			"ref": "https://html.spec.whatwg.org/multipage/webappapis.html#handler-window-onpopstate",
			"type": "FunctionBody"
		},
		"onrejectionhandled": {
			"ref": "https://html.spec.whatwg.org/multipage/webappapis.html#handler-window-onrejectionhandled",
			"type": "FunctionBody"
		},
		"onstorage": {
			"ref": "https://html.spec.whatwg.org/multipage/webappapis.html#handler-window-onstorage",
			"type": "FunctionBody"
		},
		"onunhandledrejection": {
			"ref": "https://html.spec.whatwg.org/multipage/webappapis.html#handler-window-onunhandledrejection",
			"type": "FunctionBody"
		},
		"onunload": {
			"ref": "https://html.spec.whatwg.org/multipage/webappapis.html#handler-window-onunload",
			"type": "FunctionBody"
		}
	}
}
